README.md
setup.py
setuper/__init__.py
setuper/__main__.py
setuper.egg-info/PKG-INFO
setuper.egg-info/SOURCES.txt
setuper.egg-info/dependency_links.txt
setuper.egg-info/entry_points.txt
setuper.egg-info/requires.txt
setuper.egg-info/top_level.txt