Metadata-Version: 2.1
Name: setuper
Version: 0.0.7
Summary: A Python module for installing the dependencies listed in a setuptools setup.py file.
Home-page: https://github.com/chrisgavin/setuper/
License: UNKNOWN
Platform: UNKNOWN
Classifier: Programming Language :: Python :: 3
Classifier: Programming Language :: Python :: 3.5
Classifier: Programming Language :: Python :: 3.6
Classifier: Programming Language :: Python :: 3.7
Classifier: Programming Language :: Python :: 3.8
Classifier: Programming Language :: Python :: 3 :: Only
Requires-Python: >=3.5
Provides-Extra: dev
